boss/__init__.py
boss/cli.py
boss/config.py
boss/constants.py
boss/init.py
boss/state.py
boss/tasks.py
boss/util.py
boss/api/__init__.py
boss/api/bower.py
boss/api/fs.py
boss/api/git.py
boss/api/hipchat.py
boss/api/notif.py
boss/api/runner.py
boss/api/shell.py
boss/api/slack.py
boss/api/ssh.py
boss/api/deployment/__init__.py
boss/api/deployment/buildman.py
boss/api/deployment/deployer.py
boss/api/deployment/preset/__init__.py
boss/api/deployment/preset/node.py
boss/api/deployment/preset/remote_source.py
boss/api/deployment/preset/web.py
boss/core/__init__.py
boss/core/ci.py
boss/core/env.py
boss/core/fs.py
boss/core/hashing.py
boss/core/initializer.py
boss/core/inquiries.py
boss/core/notification.py
boss/core/output.py
boss/core/remote.py
boss/core/vault.py
boss/core/constants/__init__.py
boss/core/constants/ci.py
boss/core/constants/config.py
boss/core/constants/known_scripts.py
boss/core/constants/notification.py
boss/core/constants/notification_types.py
boss/core/constants/presets.py
boss/core/util/__init__.py
boss/core/util/colors.py
boss/core/util/func.py
boss/core/util/object.py
boss/core/util/string.py
boss/core/util/ts.py
boss/core/util/types.py
boss/misc/boss.yml_template
boss/misc/fabfile.py_template
boss/misc/default_html/index.html
boss/misc/default_html/css/style.css
boss/misc/default_html/img/boss-highlight.png
boss/misc/default_html/img/boss.png
boss/misc/sample-keys/user-key
boss/misc/sample-keys/user-key.pub
boss_cli-1.0.3.dist-info/LICENSE
boss_cli-1.0.3.dist-info/METADATA
boss_cli-1.0.3.dist-info/WHEEL
boss_cli-1.0.3.dist-info/entry_points.txt
boss_cli-1.0.3.dist-info/top_level.txt
boss_cli-1.0.3.dist-info/RECORD
