Metadata-Version: 2.1
Name: boss-cli
Version: 1.0.3
Summary: Yet another pythonic deployment tool built on top of fabric.
Home-page: https://github.com/kabirbaidhya/boss-cli
Author: Kabir Baidhya
Author-email: kabirbaidhya@gmail.com
License: MIT
Keywords: cli
Platform: UNKNOWN
Classifier: Intended Audience :: Developers
Classifier: Topic :: Utilities
Classifier: Natural Language :: English
Classifier: Operating System :: OS Independent
Classifier: Programming Language :: Python :: 2.7
Requires-Dist: fabric (==1.14.1)
Requires-Dist: paramiko (==2.5)
Requires-Dist: cryptography (==2.7)
Requires-Dist: pyyaml (==5.1.1)
Requires-Dist: requests (==2.20.0)
Requires-Dist: inquirer (==2.2.0)
Requires-Dist: python-dotenv (==0.6.5)
Requires-Dist: terminaltables (==3.1.0)
Requires-Dist: click (==6.7)
Requires-Dist: hvac (==0.6.4)
Provides-Extra: dev
Requires-Dist: pytest (==3.2.3) ; extra == 'dev'
Requires-Dist: pytest-cov (==2.5.1) ; extra == 'dev'
Requires-Dist: pytest-watch (==4.2.0) ; extra == 'dev'
Requires-Dist: coverage (==4.4.1) ; extra == 'dev'
Requires-Dist: mock (==2.0.0) ; extra == 'dev'
Requires-Dist: pylint (==1.7.4) ; extra == 'dev'
Requires-Dist: autopep8 (==1.3.3) ; extra == 'dev'
Requires-Dist: mock-ssh-server (==0.3.0) ; extra == 'dev'
Requires-Dist: twine (==1.13.0) ; extra == 'dev'
